cenutils/put
snowtools/__init__.py
snowtools/DATA/EMOS_HN.Rdata
snowtools/DATA/FORCING_test_base.nc
snowtools/DATA/METADATA.xml
snowtools/DATA/OPTIONS_V8.1_NEW_OUTPUTS_NC.nam
snowtools/DATA/OPTIONS_V8.1_NEW_OUTPUTS_NC_OPER.nam
snowtools/DATA/OPTIONS_V8.1_NEW_OUTPUTS_NC_SYTRON.nam
snowtools/DATA/OPTIONS_V8.1_NEW_OUTPUTS_NC_reanalysis.nam
snowtools/DATA/OPTIONS_V8.1_NEW_OUTPUTS_NC_reanalysis_avalanches.nam
snowtools/DATA/OPTIONS_V8.1_NEW_OUTPUTS_NC_reanalysis_forprep.nam
snowtools/DATA/OPTIONS_V8.1_NEW_OUTPUTS_NC_reforecast.nam
snowtools/DATA/OPTIONS_V8_NEW_OUTPUTS_NC.nam
snowtools/DATA/OPTIONS_test_2d.nam
snowtools/DATA/OPTIONS_test_2d_pappus.nam
snowtools/DATA/PGD_test_2d.nc
snowtools/DATA/__init__.py
snowtools/DATA/images.json
snowtools/DATA/interpolate_safran.nam
snowtools/DATA/liste_malgeolocalises.txt
snowtools/DATA/massifs.cpg
snowtools/DATA/massifs.dbf
snowtools/DATA/massifs.prj
snowtools/DATA/massifs.shp
snowtools/DATA/massifs.shx
snowtools/DATA/perturbations_param.txt
snowtools/DATA/reanalyse.ini
snowtools/DATA/sta_skylines.csv
snowtools/DATA/OPER/cron_belenos
snowtools/DATA/OPER/cron_sxcen
snowtools/conf/S2M_Standard_Metadata.ini
snowtools/conf/extraction_guess_safran.ini
snowtools/conf/extraction_guess_safran_reforecast.ini
snowtools/conf/s2m_alp.ini
snowtools/conf/s2m_alp_allslopes.ini
snowtools/conf/s2m_alp_pp.ini
snowtools/conf/s2m_cor.ini
snowtools/conf/s2m_cor_allslopes.ini
snowtools/conf/s2m_jur.ini
snowtools/conf/s2m_mac.ini
snowtools/conf/s2m_postes.ini
snowtools/conf/s2m_prosnow.ini
snowtools/conf/s2m_pyr.ini
snowtools/conf/s2m_pyr_allslopes.ini
snowtools/conf/s2m_vog.ini
snowtools/conf/s2mdevnew_alp.ini
snowtools/conf/s2mdevnew_cor.ini
snowtools/conf/s2mdevnew_jur.ini
snowtools/conf/s2mdevnew_mac.ini
snowtools/conf/s2mdevnew_postes.ini
snowtools/conf/s2mdevnew_pyr.ini
snowtools/conf/s2mdevnew_vog.ini
snowtools/conf/safran.ini
snowtools/conf/safran_reanalysis.ini
snowtools/conf/safran_reforecast.ini
snowtools/interpolation/DEM.nc
snowtools-2.0.1.dist-info/LICENCE-en.txt
snowtools-2.0.1.dist-info/LICENCE.txt
snowtools-2.0.1.dist-info/METADATA
snowtools-2.0.1.dist-info/WHEEL
snowtools-2.0.1.dist-info/entry_points.txt
snowtools-2.0.1.dist-info/top_level.txt
snowtools-2.0.1.dist-info/RECORD
