Metadata-Version: 2.1
Name: snowtools
Version: 2.0.1
Summary: Snowtools is a recommended python package to pre-process, run and post-process simulations with the SURFEX-Crocus snowpack model.
Author: Snowtools team, leaded by Matthieu Lafaysse, Meteo-France
Maintainer: Snowtools team, leaded by Matthieu Lafaysse, Meteo-France
License: 
Project-URL: Homepage, https://github.com/UMR-CNRM/snowtools
Project-URL: Repository, https://github.com/UMR-CNRM/snowtools
Project-URL: Issues, https://opensource.umr-cnrm.fr/projects/snowtools_git/wiki/Procedure_for_new_users
Classifier: Operating System :: POSIX :: Linux
Classifier: Programming Language :: Python :: 3.6
Classifier: Programming Language :: Python :: 3.7
Classifier: Programming Language :: Python :: 3.8
Classifier: Programming Language :: Python :: 3.9
Classifier: Programming Language :: Python :: 3.10
Classifier: Topic :: Scientific/Engineering
Classifier: License :: CeCILL-C Free Software License Agreement (CECILL-C)
Requires-Python: >=3.6
License-File: LICENCE-en.txt
License-File: LICENCE.txt
Requires-Dist: matplotlib
Requires-Dist: netCDF4
Requires-Dist: numpy
Requires-Dist: scipy
Requires-Dist: python-dateutil
Requires-Dist: pyproj
Requires-Dist: shapely
Requires-Dist: psycopg2
Requires-Dist: pyshp
Requires-Dist: pandas
Requires-Dist: xarray
Requires-Dist: cartopy
Requires-Dist: bronx
